rapidxmltojson.cpython-311-x86_64-linux-gnu.so
rapidxmltojson-0.2.5.dist-info/RECORD
rapidxmltojson-0.2.5.dist-info/top_level.txt
rapidxmltojson-0.2.5.dist-info/LICENSE
rapidxmltojson-0.2.5.dist-info/WHEEL
rapidxmltojson-0.2.5.dist-info/METADATA
