Metadata-Version: 2.1
Name: rapidxmltojson
Version: 0.2.5
Summary: rapidxmltojson
Author-email: Alisher Nazarkhanov <nazarkhanov.alisher.dev@gmail.com>
Project-URL: Homepage, https://github.com/nazarkhanov/rapidxmltojson
Project-URL: Bug Tracker, https://github.com/nazarkhanov/rapidxmltojson/issues
Classifier: Development Status :: 4 - Beta
Classifier: Intended Audience :: Developers
Classifier: License :: OSI Approved :: MIT License
Classifier: Programming Language :: Python :: 3
Classifier: Topic :: Text Processing :: Markup :: XML
Requires-Python: >=3.8
License-File: LICENSE
